mcjar.py
mcjar-0.0.2.data/data/MCJAR_README.md
mcjar-0.0.2.dist-info/licenses/COPYING.md
mcjar-0.0.2.dist-info/licenses/COPYING_CODE.txt
mcjar-0.0.2.dist-info/licenses/COPYING_DOCS.txt
mcjar-0.0.2.dist-info/METADATA
mcjar-0.0.2.dist-info/WHEEL
mcjar-0.0.2.dist-info/entry_points.txt
mcjar-0.0.2.dist-info/top_level.txt
mcjar-0.0.2.dist-info/RECORD
