Metadata-Version: 2.4
Name: mcjar
Version: 0.0.2
License-File: COPYING.md
License-File: COPYING_CODE.txt
License-File: COPYING_DOCS.txt
Dynamic: description
Dynamic: description-content-type
Dynamic: license-file
